pyvaem/__init__.py
pyvaem/config.py
pyvaem/driver.py
pyvaem/utils.py
pyvaem-1.0.2.dist-info/LICENSE
pyvaem-1.0.2.dist-info/METADATA
pyvaem-1.0.2.dist-info/WHEEL
pyvaem-1.0.2.dist-info/RECORD
