Metadata-Version: 2.1
Name: pyvaem
Version: 1.0.2
Summary: Python API for VAEM Festo valve control module
Home-page: https://github.com/jlmoraleshellin/pyvaem
License: Apache-2.0
Author: Jose
Author-email: jlmoraleshellin@gmail.com
Requires-Python: >=3.10,<4.0
Classifier: License :: OSI Approved :: Apache Software License
Classifier: Programming Language :: Python :: 3
Classifier: Programming Language :: Python :: 3.10
Classifier: Programming Language :: Python :: 3.11
Classifier: Programming Language :: Python :: 3.12
Classifier: Programming Language :: Python :: 3.13
Requires-Dist: pymodbus (>=3.0.0,<4.0.0)
Project-URL: Repository, https://github.com/jlmoraleshellin/pyvaem
